Workbook

Sheet サマリー
A1: ULTRA MART 多店舗展開 事業計画（ドラフト）
A2: 作成日: 2026年8月3日 ／ 出典: ULTRA MART TOKYO 2026年7月実績（管理表）
A3: 緑字＝他シート参照。コスト・展開スケジュールはすべて「前提条件」シートの仮置き値で、変更すると全体に反映されます。
A5: ■ 東京1号店 実績ハイライト（2026/7/10〜7/31・22日間）
A6: 売上高（税抜） | B6: =東京実績分析!B33 -> 17272258 | D6: オープン3日間の日販 約141万円 → 第4週 約50万円と、開業景気は3週間で約1/3に減衰。
A7: 日販平均 | B7: =東京実績分析!B34 -> 785102.64 | D7: 安定期の日販は平日 約50万円・土日 約65万円（詳細は「東京実績分析」シート）。
A8: 来店者数 | B8: =東京実績分析!B35 -> 26234
A9: 客単価（税抜） | B9: =東京実績分析!B37 -> 3343.4491
A10: 買上率 | B10: =東京実績分析!B38 -> 0.19692003
A12: ■ 展開スケジュール（前提条件シートで変更可）
A13: 店舗 | B13: 開業時期 | C13: 出店投資
A14: 東京 | B14: 2026年7月 開業済 | C14: =前提条件!B38 -> 30000000
A15: 大阪 | B15: 2026年11月 開業想定 | C15: =前提条件!C38 -> 25000000
A16: 福岡 | B16: 2027年3月 開業想定 | C16: =前提条件!D38 -> 20000000
A18: ■ 年度別計画（税抜・円）
A19: 項目 | B19: 1年目 (2026/7〜2027/6) | C19: 2年目 (2027/7〜2028/6)
A20: 売上高 東京 | B20: =月次計画!AA8 -> 159560558 | C20: =月次計画!AB8 -> 155116500
A21: 売上高 大阪 | B21: =月次計画!AA21 -> 92683745 | C21: =月次計画!AB21 -> 131849025
A22: 売上高 福岡 | B22: =月次計画!AA34 -> 39096558 | C22: =月次計画!AB34 -> 100825725
A23: 連結売上高 | B23: =月次計画!AA47 -> 291340861 | C23: =月次計画!AB47 -> 387791250
A24: 店舗営業利益計 | B24: =月次計画!AA48 -> 14550129 | C24: =月次計画!AB48 -> 7383968
A25: 本部費 | B25: =月次計画!AA49 -> 18000000 | C25: =月次計画!AB49 -> 18000000
A26: 連結営業利益 | B26: =月次計画!AA50 -> -3449871 | C26: =月次計画!AB50 -> -10616032
A28: ■ 安定期の店舗別 月次モデル（開業3ヶ月目以降・季節指数1.0時）
A29: 項目 | B29: 東京 | C29: 大阪 | D29: 福岡
A30: 売上高 | B30: =ROUND(前提条件!$B$10*前提条件!$B$13,0) -> 13090000 | C30: =ROUND(前提条件!$B$10*前提条件!$B$14,0) -> 11126500 | D30: =ROUND(前提条件!$B$10*前提条件!$B$15,0) -> 8508500
A31: 売上原価 | B31: =ROUND(B30*前提条件!$B$28,0) -> 5890500 | C31: =ROUND(C30*前提条件!$B$28,0) -> 5006925 | D31: =ROUND(D30*前提条件!$B$28,0) -> 3828825
A32: 売上総利益 | B32: =B30-B31 -> 7199500 | C32: =C30-C31 -> 6119575 | D32: =D30-D31 -> 4679675
A33: ロイヤリティ | B33: =ROUND(B30*前提条件!$B$29,0) -> 654500 | C33: =ROUND(C30*前提条件!$B$29,0) -> 556325 | D33: =ROUND(D30*前提条件!$B$29,0) -> 425425
A34: 家賃 | B34: =前提条件!$B$34 -> 1800000 | C34: =前提条件!$C$34 -> 1400000 | D34: =前提条件!$D$34 -> 1000000
A35: 人件費 | B35: =前提条件!$B$35 -> 1800000 | C35: =前提条件!$C$35 -> 1700000 | D35: =前提条件!$D$35 -> 1500000
A36: イベント運営費 | B36: =前提条件!$B$36 -> 900000 | C36: =前提条件!$C$36 -> 900000 | D36: =前提条件!$D$36 -> 800000
A37: その他販管費 | B37: =ROUND(B30*前提条件!$B$30,0)+前提条件!$B$37 -> 923600 | C37: =ROUND(C30*前提条件!$B$30,0)+前提条件!$C$37 -> 845060 | D37: =ROUND(D30*前提条件!$B$30,0)+前提条件!$D$37 -> 740340
A38: 減価償却費 | B38: =ROUND(前提条件!$B$38/(前提条件!$B$39*12),0) -> 500000 | C38: =ROUND(前提条件!$C$38/(前提条件!$B$39*12),0) -> 416667 | D38: =ROUND(前提条件!$D$38/(前提条件!$B$39*12),0) -> 333333
A39: 営業利益 | B39: =B32-SUM(B33:B38) -> 621400 | C39: =C32-SUM(C33:C38) -> 301523 | D39: =D32-SUM(D33:D38) -> -119423
A40: 営業利益率 | B40: =IF(B30=0,0,B39/B30) -> 0.047471352 | C40: =IF(C30=0,0,C39/C30) -> 0.027099537 | D40: =IF(D30=0,0,D39/D30) -> -0.014035729
A41: 償却前営業利益 | B41: =B39+B38 -> 1121400 | C41: =C39+C38 -> 718190 | D41: =D39+D38 -> 213910
A42: 投資回収月数（償却前利益ベース） | B42: =IF(B41<=0,"回収不能",ROUND(前提条件!$B$38/B41,0)) -> 27 | C42: =IF(C41<=0,"回収不能",ROUND(前提条件!$C$38/C41,0)) -> 35 | D42: =IF(D41<=0,"回収不能",ROUND(前提条件!$D$38/D41,0)) -> 93
A44: ■ 前提・留意事項
A45: 1. 売上以外のコスト（原価率・家賃・人件費・ロイヤリティ・投資額等）はすべて仮置きです。実数を「前提条件」シートに反映してください。
A46: 2. 東京の2026年7月売上のみ実績値。それ以外はすべて 基準月商×地域係数×ランプ係数×季節指数 による計画値です。
A47: 3. 東京実績はオープン景気の減衰が大きく（3週間で日販約1/3）、本計画は「安定日販48万円」を前提にしています。実際の安定水準の見極めが最重要です。
A48: 4. 集客はキャラクターグリーティング（毎日開催）に強く依存しています。出演スケジュールの持続可能性とコストが計画の前提です。
A49: 5. 売上の約2割をmofusandコラボ商品が占めており、コラボ企画の継続・入替が売上維持の鍵です。
A50: 6. ライセンス契約（ロイヤリティ・地域展開の可否）は権利元との協議事項であり、本計画には反映していません。
A51: 7. 福岡は現在の仮置きコストでは安定期に月次▲12万円と損益分岐点近傍です。軽量フォーマット（売場縮小・期間限定ポップアップ型）の検討を推奨します。
A52: 8. 現在の仮置きでは店舗営業利益計（1年目 約1,455万円）が本部費（月150万円＝年1,800万円）を下回り、連結は赤字です。本部費の圧縮（既存本社機能との共用等）か、各都市を開業景気を刈り取る期間限定ポップアップ型で回す戦略が現実的な選択肢です。
A53: 9. 開業月は月初からのフル営業を前提としています（東京同様に月中開業の場合、開業月の売上は日割りで減少します）。

Sheet 前提条件
A1: 【前提条件】ULTRA MART 多店舗展開計画
A2: 凡例: 黄色セル（青字）＝仮置きの入力値。実数が判明したら差し替えてください。それ以外の黒字セルは自動計算です。
A4: ■ 売上前提
A5: 東京 安定日販（税抜・円） | B5: 480000 | C5: 出典: 東京7月下旬実績（最終週 平日平均 約50万円）より保守的に設定
A7: 季節指数（暦月別・年平均≒1.0） | B7: 1月 | C7: 2月 | D7: 3月 | E7: 4月 | F7: 5月 | G7: 6月 | H7: 7月 | I7: 8月 | J7: 9月 | K7: 10月 | L7: 11月 | M7: 12月
B8: 0.85 | C8: 0.85 | D8: 1 | E8: 0.95 | F8: 1.05 | G8: 0.9 | H8: 1.1 | I8: 1.2 | J8: 0.95 | K8: 0.95 | L8: 0.95 | M8: 1.1
A10: 基準月商（税抜・季節指数1.0換算） | B10: =ROUND(B5*30/H8,-4) -> 13090000 | C10: 計算式: 安定日販 × 30日 ÷ 7月季節指数
A12: 地域係数（商圏規模による売上補正）
A13: 東京 | B13: 1 | C13: 基準（1号店実績）
A14: 大阪 | B14: 0.85 | C14: 仮置き。梅田・難波等の主要商業施設立地を想定
A15: 福岡 | B15: 0.65 | C15: 仮置き。天神・博多の商業施設立地を想定（商圏規模を考慮）
A17: ランプ係数（開業からの月齢による売上倍率）
A18: 開業1ヶ月目 | B18: 1.6 | C18: 東京実績: 7月(22日間)の日販785,102円を30日換算した月商約2,355万円 ≒ 基準月商×7月季節指数×1.6
A19: 開業2ヶ月目 | B19: 1.1 | C19: 東京8/1-2実績（日販約65万円/週末）からの推定
A20: 開業3ヶ月目以降 | B20: 1 | C20: 安定期
A22: ■ 出店計画（月インデックス: 1 = 2026年7月）
A23: 東京 | B23: 1 | C23: 2026年7月10日 開業済（実績反映）
A24: 大阪 | B24: 5 | C24: 2026年11月 開業想定（物件契約〜内装で約3ヶ月を想定）
A25: 福岡 | B25: 9 | C25: 2027年3月 開業想定（大阪の立ち上げ検証後）
A27: ■ コスト前提（売上比率）※すべて仮置き・要実数反映
A28: 売上原価率 | B28: 0.45 | C28: 仮置き。キャラクター雑貨物販の一般的水準（40〜50%）の中央値
A29: ライセンスロイヤリティ率 | B29: 0.05 | C29: 仮置き。ライセンス契約条件により大きく変動（要確認）
A30: その他販管費（変動）率 | B30: 0.04 | C30: 仮置き。決済手数料・包材・物流等
A32: ■ コスト前提（店舗別・月額）※すべて仮置き・要実数反映
A33: 項目 | B33: 東京 | C33: 大阪 | D33: 福岡 | E33: 備考
A34: 家賃（月額） | B34: 1800000 | C34: 1400000 | D34: 1000000 | E34: 仮置き。商業施設内区画を想定。歩合家賃契約の場合は要修正
A35: 人件費（月額） | B35: 1800000 | C35: 1700000 | D35: 1500000 | E35: 仮置き。販売スタッフ体制（店長1＋スタッフ4〜5名シフト）
A36: イベント運営費（月額） | B36: 900000 | C36: 900000 | D36: 800000 | E36: 仮置き。キャラクター出演・アテンド・整理券運営（毎日開催前提）
A37: その他固定費（月額） | B37: 400000 | C37: 400000 | D37: 400000 | E37: 仮置き。水道光熱・通信・警備・雑費
A38: 出店投資（内装・什器・保証金等） | B38: 30000000 | C38: 25000000 | D38: 20000000 | E38: 仮置き。東京は参考値（既払い）。減価償却の計算に使用
A39: 減価償却年数（年・定額法） | B39: 5
A41: ■ 本部費
A42: 本部費（月額・連結） | B42: 1500000 | C42: 仮置き。SV・商品企画・在庫管理等の本部機能

Sheet 月次計画
A1: 【月次計画】2026年7月〜2028年6月（税抜・円）
A2: 売上＝基準月商×地域係数×ランプ係数×季節指数（前提条件シート参照）。東京の2026年7月のみ実績値。
A3: 月インデックス | C3: 1 | D3: 2 | E3: 3 | F3: 4 | G3: 5 | H3: 6 | I3: 7 | J3: 8 | K3: 9 | L3: 10 | M3: 11 | N3: 12 | O3: 13 | P3: 14 | Q3: 15 | R3: 16 | S3: 17 | T3: 18 | U3: 19 | V3: 20 | W3: 21 | X3: 22 | Y3: 23 | Z3: 24
A4: 年月 | C4: 2026/07 | D4: 2026/08 | E4: 2026/09 | F4: 2026/10 | G4: 2026/11 | H4: 2026/12 | I4: 2027/01 | J4: 2027/02 | K4: 2027/03 | L4: 2027/04 | M4: 2027/05 | N4: 2027/06 | O4: 2027/07 | P4: 2027/08 | Q4: 2027/09 | R4: 2027/10 | S4: 2027/11 | T4: 2027/12 | U4: 2028/01 | V4: 2028/02 | W4: 2028/03 | X4: 2028/04 | Y4: 2028/05 | Z4: 2028/06 | AA4: 1年目計 (26/7-27/6) | AB4: 2年目計 (27/7-28/6)
A5: 暦月 | C5: 7 | D5: 8 | E5: 9 | F5: 10 | G5: 11 | H5: 12 | I5: 1 | J5: 2 | K5: 3 | L5: 4 | M5: 5 | N5: 6 | O5: 7 | P5: 8 | Q5: 9 | R5: 10 | S5: 11 | T5: 12 | U5: 1 | V5: 2 | W5: 3 | X5: 4 | Y5: 5 | Z5: 6
A7: ■ 東京 | B7: 2026年7月10日 開業済。26/7列は実績値（青字）
A8: 売上高 | C8: 17272258 | D8: =IF(D$3<前提条件!$B$23,0,ROUND(前提条件!$B$10*前提条件!$B$13*IF(D$3-前提条件!$B$23+1=1,前提条件!$B$18,IF(D$3-前提条件!$B$23+1=2,前提条件!$B$19,前提条件!$B$20))*INDEX(前提条件!$B$8:$M$8,D$5),0)) -> 17278800 | E8: =IF(E$3<前提条件!$B$23,0,ROUND(前提条件!$B$10*前提条件!$B$13*IF(E$3-前提条件!$B$23+1=1,前提条件!$B$18,IF(E$3-前提条件!$B$23+1=2,前提条件!$B$19,前提条件!$B$20))*INDEX(前提条件!$B$8:$M$8,E$5),0)) -> 12435500 | F8: =IF(F$3<前提条件!$B$23,0,ROUND(前提条件!$B$10*前提条件!$B$13*IF(F$3-前提条件!$B$23+1=1,前提条件!$B$18,IF(F$3-前提条件!$B$23+1=2,前提条件!$B$19,前提条件!$B$20))*INDEX(前提条件!$B$8:$M$8,F$5),0)) -> 12435500 | G8: =IF(G$3<前提条件!$B$23,0,ROUND(前提条件!$B$10*前提条件!$B$13*IF(G$3-前提条件!$B$23+1=1,前提条件!$B$18,IF(G$3-前提条件!$B$23+1=2,前提条件!$B$19,前提条件!$B$20))*INDEX(前提条件!$B$8:$M$8,G$5),0)) -> 12435500 | H8: =IF(H$3<前提条件!$B$23,0,ROUND(前提条件!$B$10*前提条件!$B$13*IF(H$3-前提条件!$B$23+1=1,前提条件!$B$18,IF(H$3-前提条件!$B$23+1=2,前提条件!$B$19,前提条件!$B$20))*INDEX(前提条件!$B$8:$M$8,H$5),0)) -> 14399000 | I8: =IF(I$3<前提条件!$B$23,0,ROUND(前提条件!$B$10*前提条件!$B$13*IF(I$3-前提条件!$B$23+1=1,前提条件!$B$18,IF(I$3-前提条件!$B$23+1=2,前提条件!$B$19,前提条件!$B$20))*INDEX(前提条件!$B$8:$M$8,I$5),0)) -> 11126500 | J8: =IF(J$3<前提条件!$B$23,0,ROUND(前提条件!$B$10*前提条件!$B$13*IF(J$3-前提条件!$B$23+1=1,前提条件!$B$18,IF(J$3-前提条件!$B$23+1=2,前提条件!$B$19,前提条件!$B$20))*INDEX(前提条件!$B$8:$M$8,J$5),0)) -> 11126500 | K8: =IF(K$3<前提条件!$B$23,0,ROUND(前提条件!$B$10*前提条件!$B$13*IF(K$3-前提条件!$B$23+1=1,前提条件!$B$18,IF(K$3-前提条件!$B$23+1=2,前提条件!$B$19,前提条件!$B$20))*INDEX(前提条件!$B$8:$M$8,K$5),0)) -> 13090000 | ... Z8: =IF(Z$3<前提条件!$B$23,0,ROUND(前提条件!$B$10*前提条件!$B$13*IF(Z$3-前提条件!$B$23+1=1,前提条件!$B$18,IF(Z$3-前提条件!$B$23+1=2,前提条件!$B$19,前提条件!$B$20))*INDEX(前提条件!$B$8:$M$8,Z$5),0)) -> 11781000 | AA8: =SUM(C8:N8) -> 159560558 | AB8: =SUM(O8:Z8) -> 155116500
A9: 売上原価 | C9: =ROUND(C8*前提条件!$B$28,0) -> 7772516 | D9: =ROUND(D8*前提条件!$B$28,0) -> 7775460 | E9: =ROUND(E8*前提条件!$B$28,0) -> 5595975 | F9: =ROUND(F8*前提条件!$B$28,0) -> 5595975 | G9: =ROUND(G8*前提条件!$B$28,0) -> 5595975 | H9: =ROUND(H8*前提条件!$B$28,0) -> 6479550 | I9: =ROUND(I8*前提条件!$B$28,0) -> 5006925 | J9: =ROUND(J8*前提条件!$B$28,0) -> 5006925 | ... Z9: =ROUND(Z8*前提条件!$B$28,0) -> 5301450 | AA9: =SUM(C9:N9) -> 71802251 | AB9: =SUM(O9:Z9) -> 69802425
A10: 売上総利益 | C10: =C8-C9 -> 9499742 | D10: =D8-D9 -> 9503340 | E10: =E8-E9 -> 6839525 | F10: =F8-F9 -> 6839525 | G10: =G8-G9 -> 6839525 | H10: =H8-H9 -> 7919450 | I10: =I8-I9 -> 6119575 | J10: =J8-J9 -> 6119575 | ... Z10: =Z8-Z9 -> 6479550 | AA10: =SUM(C10:N10) -> 87758307 | AB10: =SUM(O10:Z10) -> 85314075
A11: ロイヤリティ | C11: =ROUND(C8*前提条件!$B$29,0) -> 863613 | D11: =ROUND(D8*前提条件!$B$29,0) -> 863940 | E11: =ROUND(E8*前提条件!$B$29,0) -> 621775 | F11: =ROUND(F8*前提条件!$B$29,0) -> 621775 | G11: =ROUND(G8*前提条件!$B$29,0) -> 621775 | H11: =ROUND(H8*前提条件!$B$29,0) -> 719950 | I11: =ROUND(I8*前提条件!$B$29,0) -> 556325 | J11: =ROUND(J8*前提条件!$B$29,0) -> 556325 | ... Z11: =ROUND(Z8*前提条件!$B$29,0) -> 589050 | AA11: =SUM(C11:N11) -> 7978028 | AB11: =SUM(O11:Z11) -> 7755825
A12: 家賃 | C12: =IF(C$3>=前提条件!$B$23,前提条件!$B$34,0) -> 1800000 | D12: =IF(D$3>=前提条件!$B$23,前提条件!$B$34,0) -> 1800000 | E12: =IF(E$3>=前提条件!$B$23,前提条件!$B$34,0) -> 1800000 | F12: =IF(F$3>=前提条件!$B$23,前提条件!$B$34,0) -> 1800000 | G12: =IF(G$3>=前提条件!$B$23,前提条件!$B$34,0) -> 1800000 | H12: =IF(H$3>=前提条件!$B$23,前提条件!$B$34,0) -> 1800000 | I12: =IF(I$3>=前提条件!$B$23,前提条件!$B$34,0) -> 1800000 | J12: =IF(J$3>=前提条件!$B$23,前提条件!$B$34,0) -> 1800000 | ... Z12: =IF(Z$3>=前提条件!$B$23,前提条件!$B$34,0) -> 1800000 | AA12: =SUM(C12:N12) -> 21600000 | AB12: =SUM(O12:Z12) -> 21600000
A13: 人件費 | C13: =IF(C$3>=前提条件!$B$23,前提条件!$B$35,0) -> 1800000 | D13: =IF(D$3>=前提条件!$B$23,前提条件!$B$35,0) -> 1800000 | E13: =IF(E$3>=前提条件!$B$23,前提条件!$B$35,0) -> 1800000 | F13: =IF(F$3>=前提条件!$B$23,前提条件!$B$35,0) -> 1800000 | G13: =IF(G$3>=前提条件!$B$23,前提条件!$B$35,0) -> 1800000 | H13: =IF(H$3>=前提条件!$B$23,前提条件!$B$35,0) -> 1800000 | I13: =IF(I$3>=前提条件!$B$23,前提条件!$B$35,0) -> 1800000 | J13: =IF(J$3>=前提条件!$B$23,前提条件!$B$35,0) -> 1800000 | ... Z13: =IF(Z$3>=前提条件!$B$23,前提条件!$B$35,0) -> 1800000 | AA13: =SUM(C13:N13) -> 21600000 | AB13: =SUM(O13:Z13) -> 21600000
A14: イベント運営費 | C14: =IF(C$3>=前提条件!$B$23,前提条件!$B$36,0) -> 900000 | D14: =IF(D$3>=前提条件!$B$23,前提条件!$B$36,0) -> 900000 | E14: =IF(E$3>=前提条件!$B$23,前提条件!$B$36,0) -> 900000 | F14: =IF(F$3>=前提条件!$B$23,前提条件!$B$36,0) -> 900000 | G14: =IF(G$3>=前提条件!$B$23,前提条件!$B$36,0) -> 900000 | H14: =IF(H$3>=前提条件!$B$23,前提条件!$B$36,0) -> 900000 | I14: =IF(I$3>=前提条件!$B$23,前提条件!$B$36,0) -> 900000 | J14: =IF(J$3>=前提条件!$B$23,前提条件!$B$36,0) -> 900000 | ... Z14: =IF(Z$3>=前提条件!$B$23,前提条件!$B$36,0) -> 900000 | AA14: =SUM(C14:N14) -> 10800000 | AB14: =SUM(O14:Z14) -> 10800000
A15: その他販管費 | C15: =ROUND(C8*前提条件!$B$30,0)+IF(C$3>=前提条件!$B$23,前提条件!$B$37,0) -> 1090890 | D15: =ROUND(D8*前提条件!$B$30,0)+IF(D$3>=前提条件!$B$23,前提条件!$B$37,0) -> 1091152 | E15: =ROUND(E8*前提条件!$B$30,0)+IF(E$3>=前提条件!$B$23,前提条件!$B$37,0) -> 897420 | F15: =ROUND(F8*前提条件!$B$30,0)+IF(F$3>=前提条件!$B$23,前提条件!$B$37,0) -> 897420 | G15: =ROUND(G8*前提条件!$B$30,0)+IF(G$3>=前提条件!$B$23,前提条件!$B$37,0) -> 897420 | H15: =ROUND(H8*前提条件!$B$30,0)+IF(H$3>=前提条件!$B$23,前提条件!$B$37,0) -> 975960 | I15: =ROUND(I8*前提条件!$B$30,0)+IF(I$3>=前提条件!$B$23,前提条件!$B$37,0) -> 845060 | J15: =ROUND(J8*前提条件!$B$30,0)+IF(J$3>=前提条件!$B$23,前提条件!$B$37,0) -> 845060 | ... Z15: =ROUND(Z8*前提条件!$B$30,0)+IF(Z$3>=前提条件!$B$23,前提条件!$B$37,0) -> 871240 | AA15: =SUM(C15:N15) -> 11182422 | AB15: =SUM(O15:Z15) -> 11004660
A16: 減価償却費 | C16: =IF(C$3>=前提条件!$B$23,ROUND(前提条件!$B$38/(前提条件!$B$39*12),0),0) -> 500000 | D16: =IF(D$3>=前提条件!$B$23,ROUND(前提条件!$B$38/(前提条件!$B$39*12),0),0) -> 500000 | E16: =IF(E$3>=前提条件!$B$23,ROUND(前提条件!$B$38/(前提条件!$B$39*12),0),0) -> 500000 | F16: =IF(F$3>=前提条件!$B$23,ROUND(前提条件!$B$38/(前提条件!$B$39*12),0),0) -> 500000 | G16: =IF(G$3>=前提条件!$B$23,ROUND(前提条件!$B$38/(前提条件!$B$39*12),0),0) -> 500000 | H16: =IF(H$3>=前提条件!$B$23,ROUND(前提条件!$B$38/(前提条件!$B$39*12),0),0) -> 500000 | I16: =IF(I$3>=前提条件!$B$23,ROUND(前提条件!$B$38/(前提条件!$B$39*12),0),0) -> 500000 | J16: =IF(J$3>=前提条件!$B$23,ROUND(前提条件!$B$38/(前提条件!$B$39*12),0),0) -> 500000 | ... Z16: =IF(Z$3>=前提条件!$B$23,ROUND(前提条件!$B$38/(前提条件!$B$39*12),0),0) -> 500000 | AA16: =SUM(C16:N16) -> 6000000 | AB16: =SUM(O16:Z16) -> 6000000
A17: 営業利益 | C17: =C10-SUM(C11:C16) -> 2545239 | D17: =D10-SUM(D11:D16) -> 2548248 | E17: =E10-SUM(E11:E16) -> 320330 | F17: =F10-SUM(F11:F16) -> 320330 | G17: =G10-SUM(G11:G16) -> 320330 | H17: =H10-SUM(H11:H16) -> 1223540 | I17: =I10-SUM(I11:I16) -> -281810 | J17: =J10-SUM(J11:J16) -> -281810 | ... Z17: =Z10-SUM(Z11:Z16) -> 19260 | AA17: =SUM(C17:N17) -> 8597857 | AB17: =SUM(O17:Z17) -> 6553590
A18: 営業利益率 | C18: =IF(C8=0,0,C17/C8) -> 0.14735995 | D18: =IF(D8=0,0,D17/D8) -> 0.1474783 | E18: =IF(E8=0,0,E17/E8) -> 0.025759318 | F18: =IF(F8=0,0,F17/F8) -> 0.025759318 | G18: =IF(G8=0,0,G17/G8) -> 0.025759318 | H18: =IF(H8=0,0,H17/H8) -> 0.084973957 | I18: =IF(I8=0,0,I17/I8) -> -0.025327821 | J18: =IF(J8=0,0,J17/J8) -> -0.025327821 | ... AB18: =IF(AB8=0,0,AB17/AB8) -> 0.042249471
A20: ■ 大阪 | B20: 開業月は前提条件シートで変更可
A21: 売上高 | C21: =IF(C$3<前提条件!$B$24,0,ROUND(前提条件!$B$10*前提条件!$B$14*IF(C$3-前提条件!$B$24+1=1,前提条件!$B$18,IF(C$3-前提条件!$B$24+1=2,前提条件!$B$19,前提条件!$B$20))*INDEX(前提条件!$B$8:$M$8,C$5),0)) -> 0 | D21: =IF(D$3<前提条件!$B$24,0,ROUND(前提条件!$B$10*前提条件!$B$14*IF(D$3-前提条件!$B$24+1=1,前提条件!$B$18,IF(D$3-前提条件!$B$24+1=2,前提条件!$B$19,前提条件!$B$20))*INDEX(前提条件!$B$8:$M$8,D$5),0)) -> 0 | E21: =IF(E$3<前提条件!$B$24,0,ROUND(前提条件!$B$10*前提条件!$B$14*IF(E$3-前提条件!$B$24+1=1,前提条件!$B$18,IF(E$3-前提条件!$B$24+1=2,前提条件!$B$19,前提条件!$B$20))*INDEX(前提条件!$B$8:$M$8,E$5),0)) -> 0 | F21: =IF(F$3<前提条件!$B$24,0,ROUND(前提条件!$B$10*前提条件!$B$14*IF(F$3-前提条件!$B$24+1=1,前提条件!$B$18,IF(F$3-前提条件!$B$24+1=2,前提条件!$B$19,前提条件!$B$20))*INDEX(前提条件!$B$8:$M$8,F$5),0)) -> 0 | G21: =IF(G$3<前提条件!$B$24,0,ROUND(前提条件!$B$10*前提条件!$B$14*IF(G$3-前提条件!$B$24+1=1,前提条件!$B$18,IF(G$3-前提条件!$B$24+1=2,前提条件!$B$19,前提条件!$B$20))*INDEX(前提条件!$B$8:$M$8,G$5),0)) -> 16912280 | H21: =IF(H$3<前提条件!$B$24,0,ROUND(前提条件!$B$10*前提条件!$B$14*IF(H$3-前提条件!$B$24+1=1,前提条件!$B$18,IF(H$3-前提条件!$B$24+1=2,前提条件!$B$19,前提条件!$B$20))*INDEX(前提条件!$B$8:$M$8,H$5),0)) -> 13463065 | I21: =IF(I$3<前提条件!$B$24,0,ROUND(前提条件!$B$10*前提条件!$B$14*IF(I$3-前提条件!$B$24+1=1,前提条件!$B$18,IF(I$3-前提条件!$B$24+1=2,前提条件!$B$19,前提条件!$B$20))*INDEX(前提条件!$B$8:$M$8,I$5),0)) -> 9457525 | J21: =IF(J$3<前提条件!$B$24,0,ROUND(前提条件!$B$10*前提条件!$B$14*IF(J$3-前提条件!$B$24+1=1,前提条件!$B$18,IF(J$3-前提条件!$B$24+1=2,前提条件!$B$19,前提条件!$B$20))*INDEX(前提条件!$B$8:$M$8,J$5),0)) -> 9457525 | ... Z21: =IF(Z$3<前提条件!$B$24,0,ROUND(前提条件!$B$10*前提条件!$B$14*IF(Z$3-前提条件!$B$24+1=1,前提条件!$B$18,IF(Z$3-前提条件!$B$24+1=2,前提条件!$B$19,前提条件!$B$20))*INDEX(前提条件!$B$8:$M$8,Z$5),0)) -> 10013850 | AA21: =SUM(C21:N21) -> 92683745 | AB21: =SUM(O21:Z21) -> 131849025
A22: 売上原価 | C22: =ROUND(C21*前提条件!$B$28,0) -> 0 | D22: =ROUND(D21*前提条件!$B$28,0) -> 0 | E22: =ROUND(E21*前提条件!$B$28,0) -> 0 | F22: =ROUND(F21*前提条件!$B$28,0) -> 0 | G22: =ROUND(G21*前提条件!$B$28,0) -> 7610526 | H22: =ROUND(H21*前提条件!$B$28,0) -> 6058379 | I22: =ROUND(I21*前提条件!$B$28,0) -> 4255886 | J22: =ROUND(J21*前提条件!$B$28,0) -> 4255886 | ... Z22: =ROUND(Z21*前提条件!$B$28,0) -> 4506233 | AA22: =SUM(C22:N22) -> 41707685 | AB22: =SUM(O22:Z22) -> 59332063
A23: 売上総利益 | C23: =C21-C22 -> 0 | D23: =D21-D22 -> 0 | E23: =E21-E22 -> 0 | F23: =F21-F22 -> 0 | G23: =G21-G22 -> 9301754 | H23: =H21-H22 -> 7404686 | I23: =I21-I22 -> 5201639 | J23: =J21-J22 -> 5201639 | ... Z23: =Z21-Z22 -> 5507617 | AA23: =SUM(C23:N23) -> 50976060 | AB23: =SUM(O23:Z23) -> 72516962
A24: ロイヤリティ | C24: =ROUND(C21*前提条件!$B$29,0) -> 0 | D24: =ROUND(D21*前提条件!$B$29,0) -> 0 | E24: =ROUND(E21*前提条件!$B$29,0) -> 0 | F24: =ROUND(F21*前提条件!$B$29,0) -> 0 | G24: =ROUND(G21*前提条件!$B$29,0) -> 845614 | H24: =ROUND(H21*前提条件!$B$29,0) -> 673153 | I24: =ROUND(I21*前提条件!$B$29,0) -> 472876 | J24: =ROUND(J21*前提条件!$B$29,0) -> 472876 | ... Z24: =ROUND(Z21*前提条件!$B$29,0) -> 500693 | AA24: =SUM(C24:N24) -> 4634187 | AB24: =SUM(O24:Z24) -> 6592453
A25: 家賃 | C25: =IF(C$3>=前提条件!$B$24,前提条件!$C$34,0) -> 0 | D25: =IF(D$3>=前提条件!$B$24,前提条件!$C$34,0) -> 0 | E25: =IF(E$3>=前提条件!$B$24,前提条件!$C$34,0) -> 0 | F25: =IF(F$3>=前提条件!$B$24,前提条件!$C$34,0) -> 0 | G25: =IF(G$3>=前提条件!$B$24,前提条件!$C$34,0) -> 1400000 | H25: =IF(H$3>=前提条件!$B$24,前提条件!$C$34,0) -> 1400000 | I25: =IF(I$3>=前提条件!$B$24,前提条件!$C$34,0) -> 1400000 | J25: =IF(J$3>=前提条件!$B$24,前提条件!$C$34,0) -> 1400000 | ... Z25: =IF(Z$3>=前提条件!$B$24,前提条件!$C$34,0) -> 1400000 | AA25: =SUM(C25:N25) -> 11200000 | AB25: =SUM(O25:Z25) -> 16800000
A26: 人件費 | C26: =IF(C$3>=前提条件!$B$24,前提条件!$C$35,0) -> 0 | D26: =IF(D$3>=前提条件!$B$24,前提条件!$C$35,0) -> 0 | E26: =IF(E$3>=前提条件!$B$24,前提条件!$C$35,0) -> 0 | F26: =IF(F$3>=前提条件!$B$24,前提条件!$C$35,0) -> 0 | G26: =IF(G$3>=前提条件!$B$24,前提条件!$C$35,0) -> 1700000 | H26: =IF(H$3>=前提条件!$B$24,前提条件!$C$35,0) -> 1700000 | I26: =IF(I$3>=前提条件!$B$24,前提条件!$C$35,0) -> 1700000 | J26: =IF(J$3>=前提条件!$B$24,前提条件!$C$35,0) -> 1700000 | ... Z26: =IF(Z$3>=前提条件!$B$24,前提条件!$C$35,0) -> 1700000 | AA26: =SUM(C26:N26) -> 13600000 | AB26: =SUM(O26:Z26) -> 20400000
A27: イベント運営費 | C27: =IF(C$3>=前提条件!$B$24,前提条件!$C$36,0) -> 0 | D27: =IF(D$3>=前提条件!$B$24,前提条件!$C$36,0) -> 0 | E27: =IF(E$3>=前提条件!$B$24,前提条件!$C$36,0) -> 0 | F27: =IF(F$3>=前提条件!$B$24,前提条件!$C$36,0) -> 0 | G27: =IF(G$3>=前提条件!$B$24,前提条件!$C$36,0) -> 900000 | H27: =IF(H$3>=前提条件!$B$24,前提条件!$C$36,0) -> 900000 | I27: =IF(I$3>=前提条件!$B$24,前提条件!$C$36,0) -> 900000 | J27: =IF(J$3>=前提条件!$B$24,前提条件!$C$36,0) -> 900000 | ... Z27: =IF(Z$3>=前提条件!$B$24,前提条件!$C$36,0) -> 900000 | AA27: =SUM(C27:N27) -> 7200000 | AB27: =SUM(O27:Z27) -> 10800000
A28: その他販管費 | C28: =ROUND(C21*前提条件!$B$30,0)+IF(C$3>=前提条件!$B$24,前提条件!$C$37,0) -> 0 | D28: =ROUND(D21*前提条件!$B$30,0)+IF(D$3>=前提条件!$B$24,前提条件!$C$37,0) -> 0 | E28: =ROUND(E21*前提条件!$B$30,0)+IF(E$3>=前提条件!$B$24,前提条件!$C$37,0) -> 0 | F28: =ROUND(F21*前提条件!$B$30,0)+IF(F$3>=前提条件!$B$24,前提条件!$C$37,0) -> 0 | G28: =ROUND(G21*前提条件!$B$30,0)+IF(G$3>=前提条件!$B$24,前提条件!$C$37,0) -> 1076491 | H28: =ROUND(H21*前提条件!$B$30,0)+IF(H$3>=前提条件!$B$24,前提条件!$C$37,0) -> 938523 | I28: =ROUND(I21*前提条件!$B$30,0)+IF(I$3>=前提条件!$B$24,前提条件!$C$37,0) -> 778301 | J28: =ROUND(J21*前提条件!$B$30,0)+IF(J$3>=前提条件!$B$24,前提条件!$C$37,0) -> 778301 | ... Z28: =ROUND(Z21*前提条件!$B$30,0)+IF(Z$3>=前提条件!$B$24,前提条件!$C$37,0) -> 800554 | AA28: =SUM(C28:N28) -> 6907350 | AB28: =SUM(O28:Z28) -> 10073961
A29: 減価償却費 | C29: =IF(C$3>=前提条件!$B$24,ROUND(前提条件!$C$38/(前提条件!$B$39*12),0),0) -> 0 | D29: =IF(D$3>=前提条件!$B$24,ROUND(前提条件!$C$38/(前提条件!$B$39*12),0),0) -> 0 | E29: =IF(E$3>=前提条件!$B$24,ROUND(前提条件!$C$38/(前提条件!$B$39*12),0),0) -> 0 | F29: =IF(F$3>=前提条件!$B$24,ROUND(前提条件!$C$38/(前提条件!$B$39*12),0),0) -> 0 | G29: =IF(G$3>=前提条件!$B$24,ROUND(前提条件!$C$38/(前提条件!$B$39*12),0),0) -> 416667 | H29: =IF(H$3>=前提条件!$B$24,ROUND(前提条件!$C$38/(前提条件!$B$39*12),0),0) -> 416667 | I29: =IF(I$3>=前提条件!$B$24,ROUND(前提条件!$C$38/(前提条件!$B$39*12),0),0) -> 416667 | J29: =IF(J$3>=前提条件!$B$24,ROUND(前提条件!$C$38/(前提条件!$B$39*12),0),0) -> 416667 | ... Z29: =IF(Z$3>=前提条件!$B$24,ROUND(前提条件!$C$38/(前提条件!$B$39*12),0),0) -> 416667 | AA29: =SUM(C29:N29) -> 3333336 | AB29: =SUM(O29:Z29) -> 5000004
A30: 営業利益 | C30: =C23-SUM(C24:C29) -> 0 | D30: =D23-SUM(D24:D29) -> 0 | E30: =E23-SUM(E24:E29) -> 0 | F30: =F23-SUM(F24:F29) -> 0 | G30: =G23-SUM(G24:G29) -> 2962982 | H30: =H23-SUM(H24:H29) -> 1376343 | I30: =I23-SUM(I24:I29) -> -466205 | J30: =J23-SUM(J24:J29) -> -466205 | ... Z30: =Z23-SUM(Z24:Z29) -> -210297 | AA30: =SUM(C30:N30) -> 4101187 | AB30: =SUM(O30:Z30) -> 2850544
A31: 営業利益率 | C31: =IF(C21=0,0,C30/C21) -> 0 | D31: =IF(D21=0,0,D30/D21) -> 0 | E31: =IF(E21=0,0,E30/E21) -> 0 | F31: =IF(F21=0,0,F30/F21) -> 0 | G31: =IF(G21=0,0,G30/G21) -> 0.17519708 | H31: =IF(H21=0,0,H30/H21) -> 0.10223103 | I31: =IF(I21=0,0,I30/I21) -> -0.049294609 | J31: =IF(J21=0,0,J30/J21) -> -0.049294609 | ... AB31: =IF(AB21=0,0,AB30/AB21) -> 0.021619758
A33: ■ 福岡 | B33: 開業月は前提条件シートで変更可
A34: 売上高 | C34: =IF(C$3<前提条件!$B$25,0,ROUND(前提条件!$B$10*前提条件!$B$15*IF(C$3-前提条件!$B$25+1=1,前提条件!$B$18,IF(C$3-前提条件!$B$25+1=2,前提条件!$B$19,前提条件!$B$20))*INDEX(前提条件!$B$8:$M$8,C$5),0)) -> 0 | D34: =IF(D$3<前提条件!$B$25,0,ROUND(前提条件!$B$10*前提条件!$B$15*IF(D$3-前提条件!$B$25+1=1,前提条件!$B$18,IF(D$3-前提条件!$B$25+1=2,前提条件!$B$19,前提条件!$B$20))*INDEX(前提条件!$B$8:$M$8,D$5),0)) -> 0 | E34: =IF(E$3<前提条件!$B$25,0,ROUND(前提条件!$B$10*前提条件!$B$15*IF(E$3-前提条件!$B$25+1=1,前提条件!$B$18,IF(E$3-前提条件!$B$25+1=2,前提条件!$B$19,前提条件!$B$20))*INDEX(前提条件!$B$8:$M$8,E$5),0)) -> 0 | F34: =IF(F$3<前提条件!$B$25,0,ROUND(前提条件!$B$10*前提条件!$B$15*IF(F$3-前提条件!$B$25+1=1,前提条件!$B$18,IF(F$3-前提条件!$B$25+1=2,前提条件!$B$19,前提条件!$B$20))*INDEX(前提条件!$B$8:$M$8,F$5),0)) -> 0 | G34: =IF(G$3<前提条件!$B$25,0,ROUND(前提条件!$B$10*前提条件!$B$15*IF(G$3-前提条件!$B$25+1=1,前提条件!$B$18,IF(G$3-前提条件!$B$25+1=2,前提条件!$B$19,前提条件!$B$20))*INDEX(前提条件!$B$8:$M$8,G$5),0)) -> 0 | H34: =IF(H$3<前提条件!$B$25,0,ROUND(前提条件!$B$10*前提条件!$B$15*IF(H$3-前提条件!$B$25+1=1,前提条件!$B$18,IF(H$3-前提条件!$B$25+1=2,前提条件!$B$19,前提条件!$B$20))*INDEX(前提条件!$B$8:$M$8,H$5),0)) -> 0 | I34: =IF(I$3<前提条件!$B$25,0,ROUND(前提条件!$B$10*前提条件!$B$15*IF(I$3-前提条件!$B$25+1=1,前提条件!$B$18,IF(I$3-前提条件!$B$25+1=2,前提条件!$B$19,前提条件!$B$20))*INDEX(前提条件!$B$8:$M$8,I$5),0)) -> 0 | J34: =IF(J$3<前提条件!$B$25,0,ROUND(前提条件!$B$10*前提条件!$B$15*IF(J$3-前提条件!$B$25+1=1,前提条件!$B$18,IF(J$3-前提条件!$B$25+1=2,前提条件!$B$19,前提条件!$B$20))*INDEX(前提条件!$B$8:$M$8,J$5),0)) -> 0 | ... Z34: =IF(Z$3<前提条件!$B$25,0,ROUND(前提条件!$B$10*前提条件!$B$15*IF(Z$3-前提条件!$B$25+1=1,前提条件!$B$18,IF(Z$3-前提条件!$B$25+1=2,前提条件!$B$19,前提条件!$B$20))*INDEX(前提条件!$B$8:$M$8,Z$5),0)) -> 7657650 | AA34: =SUM(C34:N34) -> 39096558 | AB34: =SUM(O34:Z34) -> 100825725
A35: 売上原価 | C35: =ROUND(C34*前提条件!$B$28,0) -> 0 | D35: =ROUND(D34*前提条件!$B$28,0) -> 0 | E35: =ROUND(E34*前提条件!$B$28,0) -> 0 | F35: =ROUND(F34*前提条件!$B$28,0) -> 0 | G35: =ROUND(G34*前提条件!$B$28,0) -> 0 | H35: =ROUND(H34*前提条件!$B$28,0) -> 0 | I35: =ROUND(I34*前提条件!$B$28,0) -> 0 | J35: =ROUND(J34*前提条件!$B$28,0) -> 0 | ... Z35: =ROUND(Z34*前提条件!$B$28,0) -> 3445943 | AA35: =SUM(C35:N35) -> 17593451 | AB35: =SUM(O35:Z35) -> 45371578
A36: 売上総利益 | C36: =C34-C35 -> 0 | D36: =D34-D35 -> 0 | E36: =E34-E35 -> 0 | F36: =F34-F35 -> 0 | G36: =G34-G35 -> 0 | H36: =H34-H35 -> 0 | I36: =I34-I35 -> 0 | J36: =J34-J35 -> 0 | ... Z36: =Z34-Z35 -> 4211707 | AA36: =SUM(C36:N36) -> 21503107 | AB36: =SUM(O36:Z36) -> 55454147
A37: ロイヤリティ | C37: =ROUND(C34*前提条件!$B$29,0) -> 0 | D37: =ROUND(D34*前提条件!$B$29,0) -> 0 | E37: =ROUND(E34*前提条件!$B$29,0) -> 0 | F37: =ROUND(F34*前提条件!$B$29,0) -> 0 | G37: =ROUND(G34*前提条件!$B$29,0) -> 0 | H37: =ROUND(H34*前提条件!$B$29,0) -> 0 | I37: =ROUND(I34*前提条件!$B$29,0) -> 0 | J37: =ROUND(J34*前提条件!$B$29,0) -> 0 | ... Z37: =ROUND(Z34*前提条件!$B$29,0) -> 382883 | AA37: =SUM(C37:N37) -> 1954828 | AB37: =SUM(O37:Z37) -> 5041288
A38: 家賃 | C38: =IF(C$3>=前提条件!$B$25,前提条件!$D$34,0) -> 0 | D38: =IF(D$3>=前提条件!$B$25,前提条件!$D$34,0) -> 0 | E38: =IF(E$3>=前提条件!$B$25,前提条件!$D$34,0) -> 0 | F38: =IF(F$3>=前提条件!$B$25,前提条件!$D$34,0) -> 0 | G38: =IF(G$3>=前提条件!$B$25,前提条件!$D$34,0) -> 0 | H38: =IF(H$3>=前提条件!$B$25,前提条件!$D$34,0) -> 0 | I38: =IF(I$3>=前提条件!$B$25,前提条件!$D$34,0) -> 0 | J38: =IF(J$3>=前提条件!$B$25,前提条件!$D$34,0) -> 0 | ... Z38: =IF(Z$3>=前提条件!$B$25,前提条件!$D$34,0) -> 1000000 | AA38: =SUM(C38:N38) -> 4000000 | AB38: =SUM(O38:Z38) -> 12000000
A39: 人件費 | C39: =IF(C$3>=前提条件!$B$25,前提条件!$D$35,0) -> 0 | D39: =IF(D$3>=前提条件!$B$25,前提条件!$D$35,0) -> 0 | E39: =IF(E$3>=前提条件!$B$25,前提条件!$D$35,0) -> 0 | F39: =IF(F$3>=前提条件!$B$25,前提条件!$D$35,0) -> 0 | G39: =IF(G$3>=前提条件!$B$25,前提条件!$D$35,0) -> 0 | H39: =IF(H$3>=前提条件!$B$25,前提条件!$D$35,0) -> 0 | I39: =IF(I$3>=前提条件!$B$25,前提条件!$D$35,0) -> 0 | J39: =IF(J$3>=前提条件!$B$25,前提条件!$D$35,0) -> 0 | ... Z39: =IF(Z$3>=前提条件!$B$25,前提条件!$D$35,0) -> 1500000 | AA39: =SUM(C39:N39) -> 6000000 | AB39: =SUM(O39:Z39) -> 18000000
A40: イベント運営費 | C40: =IF(C$3>=前提条件!$B$25,前提条件!$D$36,0) -> 0 | D40: =IF(D$3>=前提条件!$B$25,前提条件!$D$36,0) -> 0 | E40: =IF(E$3>=前提条件!$B$25,前提条件!$D$36,0) -> 0 | F40: =IF(F$3>=前提条件!$B$25,前提条件!$D$36,0) -> 0 | G40: =IF(G$3>=前提条件!$B$25,前提条件!$D$36,0) -> 0 | H40: =IF(H$3>=前提条件!$B$25,前提条件!$D$36,0) -> 0 | I40: =IF(I$3>=前提条件!$B$25,前提条件!$D$36,0) -> 0 | J40: =IF(J$3>=前提条件!$B$25,前提条件!$D$36,0) -> 0 | ... Z40: =IF(Z$3>=前提条件!$B$25,前提条件!$D$36,0) -> 800000 | AA40: =SUM(C40:N40) -> 3200000 | AB40: =SUM(O40:Z40) -> 9600000
A41: その他販管費 | C41: =ROUND(C34*前提条件!$B$30,0)+IF(C$3>=前提条件!$B$25,前提条件!$D$37,0) -> 0 | D41: =ROUND(D34*前提条件!$B$30,0)+IF(D$3>=前提条件!$B$25,前提条件!$D$37,0) -> 0 | E41: =ROUND(E34*前提条件!$B$30,0)+IF(E$3>=前提条件!$B$25,前提条件!$D$37,0) -> 0 | F41: =ROUND(F34*前提条件!$B$30,0)+IF(F$3>=前提条件!$B$25,前提条件!$D$37,0) -> 0 | G41: =ROUND(G34*前提条件!$B$30,0)+IF(G$3>=前提条件!$B$25,前提条件!$D$37,0) -> 0 | H41: =ROUND(H34*前提条件!$B$30,0)+IF(H$3>=前提条件!$B$25,前提条件!$D$37,0) -> 0 | I41: =ROUND(I34*前提条件!$B$30,0)+IF(I$3>=前提条件!$B$25,前提条件!$D$37,0) -> 0 | J41: =ROUND(J34*前提条件!$B$30,0)+IF(J$3>=前提条件!$B$25,前提条件!$D$37,0) -> 0 | ... Z41: =ROUND(Z34*前提条件!$B$30,0)+IF(Z$3>=前提条件!$B$25,前提条件!$D$37,0) -> 706306 | AA41: =SUM(C41:N41) -> 3163862 | AB41: =SUM(O41:Z41) -> 8833029
A42: 減価償却費 | C42: =IF(C$3>=前提条件!$B$25,ROUND(前提条件!$D$38/(前提条件!$B$39*12),0),0) -> 0 | D42: =IF(D$3>=前提条件!$B$25,ROUND(前提条件!$D$38/(前提条件!$B$39*12),0),0) -> 0 | E42: =IF(E$3>=前提条件!$B$25,ROUND(前提条件!$D$38/(前提条件!$B$39*12),0),0) -> 0 | F42: =IF(F$3>=前提条件!$B$25,ROUND(前提条件!$D$38/(前提条件!$B$39*12),0),0) -> 0 | G42: =IF(G$3>=前提条件!$B$25,ROUND(前提条件!$D$38/(前提条件!$B$39*12),0),0) -> 0 | H42: =IF(H$3>=前提条件!$B$25,ROUND(前提条件!$D$38/(前提条件!$B$39*12),0),0) -> 0 | I42: =IF(I$3>=前提条件!$B$25,ROUND(前提条件!$D$38/(前提条件!$B$39*12),0),0) -> 0 | J42: =IF(J$3>=前提条件!$B$25,ROUND(前提条件!$D$38/(前提条件!$B$39*12),0),0) -> 0 | ... Z42: =IF(Z$3>=前提条件!$B$25,ROUND(前提条件!$D$38/(前提条件!$B$39*12),0),0) -> 333333 | AA42: =SUM(C42:N42) -> 1333332 | AB42: =SUM(O42:Z42) -> 3999996
A43: 営業利益 | C43: =C36-SUM(C37:C42) -> 0 | D43: =D36-SUM(D37:D42) -> 0 | E43: =E36-SUM(E37:E42) -> 0 | F43: =F36-SUM(F37:F42) -> 0 | G43: =G36-SUM(G37:G42) -> 0 | H43: =H36-SUM(H37:H42) -> 0 | I43: =I36-SUM(I37:I42) -> 0 | J43: =J36-SUM(J37:J42) -> 0 | ... Z43: =Z36-SUM(Z37:Z42) -> -510815 | AA43: =SUM(C43:N43) -> 1851085 | AB43: =SUM(O43:Z43) -> -2020166
A44: 営業利益率 | C44: =IF(C34=0,0,C43/C34) -> 0 | D44: =IF(D34=0,0,D43/D34) -> 0 | E44: =IF(E34=0,0,E43/E34) -> 0 | F44: =IF(F34=0,0,F43/F34) -> 0 | G44: =IF(G34=0,0,G43/G34) -> 0 | H44: =IF(H34=0,0,H43/H34) -> 0 | I44: =IF(I34=0,0,I43/I34) -> 0 | J44: =IF(J34=0,0,J43/J34) -> 0 | ... AB44: =IF(AB34=0,0,AB43/AB34) -> -0.020036216
A46: ■ 連結
A47: 売上高合計 | C47: =C8+C21+C34 -> 17272258 | D47: =D8+D21+D34 -> 17278800 | E47: =E8+E21+E34 -> 12435500 | F47: =F8+F21+F34 -> 12435500 | G47: =G8+G21+G34 -> 29347780 | H47: =H8+H21+H34 -> 27862065 | I47: =I8+I21+I34 -> 20584025 | J47: =J8+J21+J34 -> 20584025 | ... Z47: =Z8+Z21+Z34 -> 29452500 | AA47: =SUM(C47:N47) -> 291340861 | AB47: =SUM(O47:Z47) -> 387791250
A48: 店舗営業利益計 | C48: =C17+C30+C43 -> 2545239 | D48: =D17+D30+D43 -> 2548248 | E48: =E17+E30+E43 -> 320330 | F48: =F17+F30+F43 -> 320330 | G48: =G17+G30+G43 -> 3283312 | H48: =H17+H30+H43 -> 2599883 | I48: =I17+I30+I43 -> -748015 | J48: =J17+J30+J43 -> -748015 | ... Z48: =Z17+Z30+Z43 -> -701852 | AA48: =SUM(C48:N48) -> 14550129 | AB48: =SUM(O48:Z48) -> 7383968
A49: 本部費 | C49: =前提条件!$B$42 -> 1500000 | D49: =前提条件!$B$42 -> 1500000 | E49: =前提条件!$B$42 -> 1500000 | F49: =前提条件!$B$42 -> 1500000 | G49: =前提条件!$B$42 -> 1500000 | H49: =前提条件!$B$42 -> 1500000 | I49: =前提条件!$B$42 -> 1500000 | J49: =前提条件!$B$42 -> 1500000 | ... Z49: =前提条件!$B$42 -> 1500000 | AA49: =SUM(C49:N49) -> 18000000 | AB49: =SUM(O49:Z49) -> 18000000
A50: 連結営業利益 | C50: =C48-C49 -> 1045239 | D50: =D48-D49 -> 1048248 | E50: =E48-E49 -> -1179670 | F50: =F48-F49 -> -1179670 | G50: =G48-G49 -> 1783312 | H50: =H48-H49 -> 1099883 | I50: =I48-I49 -> -2248015 | J50: =J48-J49 -> -2248015 | ... Z50: =Z48-Z49 -> -2201852 | AA50: =SUM(C50:N50) -> -3449871 | AB50: =SUM(O50:Z50) -> -10616032
A51: 連結営業利益率 | C51: =IF(C47=0,0,C50/C47) -> 0.060515481 | D51: =IF(D47=0,0,D50/D47) -> 0.060666713 | E51: =IF(E47=0,0,E50/E47) -> -0.094863094 | F51: =IF(F47=0,0,F50/F47) -> -0.094863094 | G51: =IF(G47=0,0,G50/G47) -> 0.060764801 | H51: =IF(H47=0,0,H50/H47) -> 0.039476004 | I51: =IF(I47=0,0,I50/I47) -> -0.10921163 | J51: =IF(J47=0,0,J50/J47) -> -0.10921163 | ... AB51: =IF(AB47=0,0,AB50/AB47) -> -0.027375636
A52: 連結累計営業利益 | C52: =C50 -> 1045239 | D52: =C52+D50 -> 2093487 | E52: =D52+E50 -> 913817 | F52: =E52+F50 -> -265853 | G52: =F52+G50 -> 1517459 | H52: =G52+H50 -> 2617342 | I52: =H52+I50 -> 369327 | J52: =I52+J50 -> -1878688 | K52: =J52+K50 -> -226842 | ... Z52: =Y52+Z50 -> -14065903

Sheet 東京実績分析
A1: 【東京1号店 実績分析】2026年7月8日〜8月2日（税抜）
A2: 出典: ULTRA_MART管理表（7月・8月シート）。7/8-9はプレ営業。客単価・買上率は本シートで再計算。
A4: 日付 | B4: 曜日 | C4: 天気 | D4: キャラクター | E4: 売上(税抜) | F4: 来店者数 | G4: レジ客数 | H4: 客単価(税抜) | I4: 買上率
A5: 2026-07-08 | B5: 水 | E5: 2200 | G5: 1 | H5: =IF(G5=0,0,E5/G5) -> 2200 | I5: =IF(OR(F5=0,F5=""),0,G5/F5) -> 0
A6: 2026-07-09 | B6: 木 | E6: 16837 | G6: 4 | H6: =IF(G6=0,0,E6/G6) -> 4209.25 | I6: =IF(OR(F6=0,F6=""),0,G6/F6) -> 0
A7: 2026-07-10 | B7: 金 | C7: 晴 | D7: マン/バルタン | E7: 1813200 | F7: 1541 | G7: 382 | H7: =IF(G7=0,0,E7/G7) -> 4746.5969 | I7: =IF(OR(F7=0,F7=""),0,G7/F7) -> 0.24789098
A8: 2026-07-11 | B8: 土 | C8: 晴 | D8: マン/バルタン | E8: 1661212 | F8: 1060 | G8: 426 | H8: =IF(G8=0,0,E8/G8) -> 3899.5587 | I8: =IF(OR(F8=0,F8=""),0,G8/F8) -> 0.40188679
A9: 2026-07-12 | B9: 日 | C9: 曇 | D9: ティガ/ピグモン | E9: 755264 | F9: 1722 | G9: 238 | H9: =IF(G9=0,0,E9/G9) -> 3173.3782 | I9: =IF(OR(F9=0,F9=""),0,G9/F9) -> 0.13821138
A10: 2026-07-13 | B10: 月 | C10: 曇 | D10: ピグモン | E10: 700926 | F10: 1258 | G10: 184 | H10: =IF(G10=0,0,E10/G10) -> 3809.3804 | I10: =IF(OR(F10=0,F10=""),0,G10/F10) -> 0.14626391
A11: 2026-07-14 | B11: 火 | C11: 晴 | D11: バルタン | E11: 845294 | F11: 1054 | G11: 228 | H11: =IF(G11=0,0,E11/G11) -> 3707.4298 | I11: =IF(OR(F11=0,F11=""),0,G11/F11) -> 0.21631879
A12: 2026-07-15 | B12: 水 | C12: 晴 | D12: バルタン | E12: 749834 | F12: 1146 | G12: 240 | H12: =IF(G12=0,0,E12/G12) -> 3124.3083 | I12: =IF(OR(F12=0,F12=""),0,G12/F12) -> 0.20942408
A13: 2026-07-16 | B13: 木 | C13: 晴 | D13: ピグモン | E13: 815396 | F13: 1116 | G13: 248 | H13: =IF(G13=0,0,E13/G13) -> 3287.8871 | I13: =IF(OR(F13=0,F13=""),0,G13/F13) -> 0.22222222
A14: 2026-07-17 | B14: 金 | C14: 雨 | D14: バルタン | E14: 642481 | F14: 1148 | G14: 233 | H14: =IF(G14=0,0,E14/G14) -> 2757.4292 | I14: =IF(OR(F14=0,F14=""),0,G14/F14) -> 0.20296167
A15: 2026-07-18 | B15: 土 | C15: 曇 | D15: マン/バルタン | E15: 1203332 | F15: 1761 | G15: 393 | H15: =IF(G15=0,0,E15/G15) -> 3061.9135 | I15: =IF(OR(F15=0,F15=""),0,G15/F15) -> 0.22316865
A16: 2026-07-19 | B16: 日 | C16: 晴 | D16: ティガ/ピグモン | E16: 1037109 | F16: 1770 | G16: 349 | H16: =IF(G16=0,0,E16/G16) -> 2971.659 | I16: =IF(OR(F16=0,F16=""),0,G16/F16) -> 0.19717514
A17: 2026-07-20 | B17: 月 | C17: 晴 | D17: ティガ/ピグモン | E17: 704815 | F17: 1223 | G17: 247 | H17: =IF(G17=0,0,E17/G17) -> 2853.502 | I17: =IF(OR(F17=0,F17=""),0,G17/F17) -> 0.20196239
A18: 2026-07-21 | B18: 火 | C18: 晴 | D18: ブースカ | E18: 624205 | F18: 1075 | G18: 187 | H18: =IF(G18=0,0,E18/G18) -> 3337.9947 | I18: =IF(OR(F18=0,F18=""),0,G18/F18) -> 0.17395349
... A30: 2026-08-02 | B30: 日 | C30: 晴 | D30: ティガ/ピグモン | E30: 679625 | F30: 1505 | G30: 226 | H30: =IF(G30=0,0,E30/G30) -> 3007.1903 | I30: =IF(OR(F30=0,F30=""),0,G30/F30) -> 0.15016611
A32: ■ グランドオープン期間 KPI（7/10〜7/31・22日間）
A33: 売上高（税抜） | B33: =SUM(E7:E28) -> 17272258
A34: 日販平均 | B34: =AVERAGE(E7:E28) -> 785102.64
A35: 来店者数 | B35: =SUM(F7:F28) -> 26234
A36: レジ客数 | B36: =SUM(G7:G28) -> 5166
A37: 客単価（税抜） | B37: =SUM(E7:E28)/SUM(G7:G28) -> 3343.4491
A38: 買上率（レジ客数÷来店者数） | B38: =SUM(G7:G28)/SUM(F7:F28) -> 0.19692003
A40: ■ 週次推移（オープン景気の減衰）
A41: 期間 | B41: 売上計 | C41: 日販平均 | D41: 初週比
A42: オープン3日間 (7/10-12) | B42: =SUM(E7:E9) -> 4229676 | C42: =AVERAGE(E7:E9) -> 1409892 | D42: 1
A43: 第2週 (7/13-19) | B43: =SUM(E10:E16) -> 5994372 | C43: =AVERAGE(E10:E16) -> 856338.86 | D43: =C43/C42 -> 0.60737905
A44: 第3週 (7/20-26) | B44: =SUM(E17:E23) -> 4535117 | C44: =AVERAGE(E17:E23) -> 647873.86 | D44: =C44/C42 -> 0.4595202
A45: 第4週 (7/27-31) | B45: =SUM(E24:E28) -> 2513093 | C45: =AVERAGE(E24:E28) -> 502618.6 | D45: =C45/C42 -> 0.3564944
A46: 8月第1週末 (8/1-2) | B46: =SUM(E29:E30) -> 1298161 | C46: =AVERAGE(E29:E30) -> 649080.5 | D46: =C46/C42 -> 0.46037604
A48: ■ 平日／土日別 日販（7/13〜8/2・オープン3日間を除く）
A49: 土日 日販平均 | B49: =(SUMIF(B10:B30,"土",E10:E30)+SUMIF(B10:B30,"日",E10:E30))/(COUNTIF(B10:B30,"土")+COUNTIF(B10:B30,"日")) -> 824055
A50: 平日 日販平均 | B50: =(SUM(E10:E30)-SUMIF(B10:B30,"土",E10:E30)-SUMIF(B10:B30,"日",E10:E30))/(COUNT(E10:E30)-COUNTIF(B10:B30,"土")-COUNTIF(B10:B30,"日")) -> 626427.53
A51: （参考）売れ筋: mofusand×ウルトラマン コラボ3商品で約324万円（金額降順シートより）
